odoo/addons/purchase_request_to_requisition_operating_unit/README.rst
odoo/addons/purchase_request_to_requisition_operating_unit/__init__.py
odoo/addons/purchase_request_to_requisition_operating_unit/__manifest__.py
odoo/addons/purchase_request_to_requisition_operating_unit/i18n/it.po
odoo/addons/purchase_request_to_requisition_operating_unit/i18n/purchase_request_to_requisition_operating_unit.pot
odoo/addons/purchase_request_to_requisition_operating_unit/readme/CONTRIBUTORS.rst
odoo/addons/purchase_request_to_requisition_operating_unit/readme/DESCRIPTION.rst
odoo/addons/purchase_request_to_requisition_operating_unit/static/description/icon.png
odoo/addons/purchase_request_to_requisition_operating_unit/static/description/index.html
odoo/addons/purchase_request_to_requisition_operating_unit/tests/__init__.py
odoo/addons/purchase_request_to_requisition_operating_unit/tests/test_purchase_request_to_requisition_operating_unit.py
odoo/addons/purchase_request_to_requisition_operating_unit/wizard/__init__.py
odoo/addons/purchase_request_to_requisition_operating_unit/wizard/purchase_request_line_make_purchase_requisition.py
odoo14_addon_purchase_request_to_requisition_operating_unit-14.0.1.0.1.dev7.dist-info/METADATA
odoo14_addon_purchase_request_to_requisition_operating_unit-14.0.1.0.1.dev7.dist-info/WHEEL
odoo14_addon_purchase_request_to_requisition_operating_unit-14.0.1.0.1.dev7.dist-info/top_level.txt
odoo14_addon_purchase_request_to_requisition_operating_unit-14.0.1.0.1.dev7.dist-info/RECORD
