Metadata-Version: 2.1
Name: odoo14-addon-purchase_request_to_requisition_operating_unit
Version: 14.0.1.0.1.dev7
Summary: Purchase Request to Call for Bids with Operating Units
Home-page: https://github.com/OCA/operating-unit
Author: Forgeflow,Ecosoft,Serpent Consulting Services Pvt. Ltd.,Odoo Community Association (OCA)
Author-email: support@odoo-community.org
License: AGPL-3
Classifier: Programming Language :: Python
Classifier: Framework :: Odoo
Classifier: Framework :: Odoo :: 14.0
Classifier: License :: OSI Approved :: GNU Affero General Public License v3
Requires-Python: >=3.6
Requires-Dist: odoo14-addon-purchase-request-operating-unit
Requires-Dist: odoo14-addon-purchase-request-to-requisition
Requires-Dist: odoo14-addon-purchase-requisition-operating-unit
Requires-Dist: odoo<14.1dev,>=14.0a
